nexon_openapi/__init__.py
nexon_openapi/__version__.py
nexon_openapi/_base_client.py
nexon_openapi/_client.py
nexon_openapi/_compat.py
nexon_openapi/_constants.py
nexon_openapi/_exceptions.py
nexon_openapi/_models.py
nexon_openapi/_qs.py
nexon_openapi/_resource.py
nexon_openapi/_response.py
nexon_openapi/_types.py
nexon_openapi/resources/__init__.py
nexon_openapi/resources/_baram.py
nexon_openapi/resources/_baramy.py
nexon_openapi/resources/_crazy_arcade.py
nexon_openapi/resources/_fc_online.py
nexon_openapi/resources/_hit2.py
nexon_openapi/resources/_kartrush.py
nexon_openapi/resources/_mabinogi_heroes.py
nexon_openapi/resources/_maplestory.py
nexon_openapi/resources/_maplestorym.py
nexon_openapi/resources/_the_first_descendant.py
nexon_openapi/resources/_types.py
nexon_openapi/resources/_v4.py
nexon_openapi/resources/_wars_of_prasia.py
nexon_openapi/utils/__init__.py
nexon_openapi/utils/_transform.py
nexon_openapi/utils/_utils.py
nexon_openapi-0.0.9.dist-info/LICENSE
nexon_openapi-0.0.9.dist-info/METADATA
nexon_openapi-0.0.9.dist-info/WHEEL
nexon_openapi-0.0.9.dist-info/RECORD
