Metadata-Version: 2.1
Name: nexon_openapi
Version: 0.0.9
Summary: 
Author: bluewhale
Author-email: koko8624@gmail.com
Requires-Python: >=3.7,<4.0
Classifier: Programming Language :: Python :: 3
Classifier: Programming Language :: Python :: 3.7
Classifier: Programming Language :: Python :: 3.8
Classifier: Programming Language :: Python :: 3.9
Classifier: Programming Language :: Python :: 3.10
Classifier: Programming Language :: Python :: 3.11
Classifier: Programming Language :: Python :: 3.12
Requires-Dist: httpx (>=0.24.0,<0.25.0)
Requires-Dist: pydantic (>=2.5.2,<3.0.0)
